{"machines":[{"timestamp":"2026-02-26T04:36:02.3920770Z","disk":{"freeGB":281.67,"totalGB":3725.12},"processes":[{"group":"dsc","running":true,"name":"DSC exporter"},{"group":"tg","running":true,"name":"TG client"}],"machine":"DESKTOP-HIRREFE"},{"timestamp":"2026-02-26T04:21:15.5656550Z","disk":{"freeGB":406.78,"totalGB":476.07},"processes":[{"group":"dsc","running":true,"name":"DSC exporter"},{"group":"tg","running":false,"name":"TG client"}],"machine":"PRODESK1"},{"timestamp":"2026-02-26T04:24:17.5493183Z","disk":{"freeGB":349.68,"totalGB":476.05},"processes":[{"group":"dsc","running":true,"name":"DSC exporter"},{"group":"tg","running":true,"name":"TG client"}],"machine":"PRODESK2"},{"timestamp":"2026-02-26T04:26:09.6923427Z","disk":{"freeGB":275.56,"totalGB":449.56},"processes":[{"group":"dsc","running":false,"name":"DSC exporter"},{"group":"tg","running":false,"name":"TG client"}],"machine":"QUOKKA"},{"timestamp":"2026-02-26T04:30:17.2243067Z","disk":{"freeGB":233.05,"totalGB":446.48},"processes":[{"group":"dsc","running":true,"name":"DSC exporter"},{"group":"tg","running":true,"name":"TG client"}],"machine":"DESKTOP-OVAKFQ8"},{"timestamp":"2026-02-26T04:32:18.6491129Z","disk":{"freeGB":1406.82,"totalGB":1854.09},"processes":[{"group":"dsc","running":true,"name":"DSC exporter"},{"group":"tg","running":true,"name":"TG client"}],"machine":"DESKTOP-QKRT7VO"},{"timestamp":"2026-02-26T04:27:03.6435287Z","disk":{"freeGB":20.76,"totalGB":208.45},"processes":[{"group":"dsc","running":true,"name":"DSC exporter"},{"group":"tg","running":true,"name":"TG client"}],"machine":"ASPIRE-V3"},{"timestamp":"2026-02-26T04:32:17.3575491Z","disk":{"freeGB":255.12,"totalGB":953.25},"processes":[{"group":"dsc","running":false,"name":"DSC exporter"},{"group":"tg","running":true,"name":"TG client"}],"machine":"DESKTOP-6EG6J48"},{"timestamp":"2026-02-26T04:33:35.5984958Z","disk":{"freeGB":9.86,"totalGB":232.72},"processes":[{"group":"dsc","running":true,"name":"DSC exporter"},{"group":"tg","running":true,"name":"TG client"}],"machine":"DESKTOP-N4FRF9P"},{"timestamp":"2026-02-25T19:27:25.4414146Z","disk":{"freeGB":63.54,"totalGB":930.57},"processes":[{"group":"dsc","running":false,"name":"DSC exporter"},{"group":"tg","running":false,"name":"TG client"}],"machine":"ASUS2"},{"timestamp":"2026-02-26T04:27:31.7024148Z","disk":{"freeGB":398.17,"totalGB":476.05},"processes":[{"group":"dsc","running":true,"name":"DSC exporter"},{"group":"tg","running":false,"name":"TG client"}],"machine":"QIAOTHEBEST"}]}