{"machines":[{"timestamp":"2026-07-21T16:51:02.2296754Z","disk":{"freeGB":854.47,"totalGB":3725.06},"processes":[{"group":"dsc","running":false,"name":"DSC exporter"},{"group":"tg","running":false,"name":"TG client"}],"machine":"DESKTOP-HIRREFE"},{"timestamp":"2026-07-21T16:51:14.8367977Z","disk":{"freeGB":384.39,"totalGB":475.99},"processes":[{"group":"dsc","running":false,"name":"DSC exporter"},{"group":"tg","running":false,"name":"TG client"}],"machine":"PRODESK1"},{"timestamp":"2026-07-21T16:54:18.0064498Z","disk":{"freeGB":264.15,"totalGB":476.05},"processes":[{"group":"dsc","running":false,"name":"DSC exporter"},{"group":"tg","running":true,"name":"TG client"}],"machine":"PRODESK2"},{"timestamp":"2026-07-21T16:41:10.0427371Z","disk":{"freeGB":225.01,"totalGB":449.56},"processes":[{"group":"dsc","running":false,"name":"DSC exporter"},{"group":"tg","running":true,"name":"TG client"}],"machine":"QUOKKA"},{"timestamp":"2026-07-21T16:41:42.5386474Z","disk":{"freeGB":152.51,"totalGB":446.48},"processes":[{"group":"dsc","running":false,"name":"DSC exporter"},{"group":"tg","running":true,"name":"TG client"}],"needsRelogin":false,"machine":"DESKTOP-OVAKFQ8"},{"timestamp":"2026-07-21T16:47:20.0075195Z","disk":{"freeGB":1080.26,"totalGB":1853.66},"processes":[{"group":"dsc","running":false,"name":"DSC exporter"},{"group":"tg","running":true,"name":"TG client"}],"machine":"DESKTOP-QKRT7VO"},{"timestamp":"2026-07-21T15:57:02.3678661Z","disk":{"freeGB":7.61,"totalGB":208.45},"processes":[{"group":"dsc","running":false,"name":"DSC exporter"},{"group":"tg","running":true,"name":"TG client"}],"machine":"ASPIRE-V3"},{"timestamp":"2026-07-21T16:47:17.9177553Z","disk":{"freeGB":186.91,"totalGB":952.97},"processes":[{"group":"dsc","running":false,"name":"DSC exporter"},{"group":"tg","running":true,"name":"TG client"}],"machine":"DESKTOP-6EG6J48"},{"timestamp":"2026-07-21T16:51:46.4115822Z","disk":{"freeGB":50.86,"totalGB":232.72},"processes":[{"group":"dsc","running":false,"name":"DSC exporter"},{"group":"tg","running":false,"name":"TG client"}],"needsRelogin":false,"machine":"DESKTOP-N4FRF9P"},{"timestamp":"2026-07-21T11:57:24.8721867Z","disk":{"freeGB":61.43,"totalGB":930.43},"processes":[{"group":"dsc","running":false,"name":"DSC exporter"},{"group":"tg","running":false,"name":"TG client"}],"machine":"ASUS2"},{"timestamp":"2026-04-08T05:15:37.2767272Z","disk":{"freeGB":416.31,"totalGB":476.05},"processes":[{"group":"dsc","running":false,"name":"DSC exporter"},{"group":"tg","running":false,"name":"TG client"}],"needsRelogin":false,"machine":"QIAOTHEBEST"},{"timestamp":"2026-07-21T16:46:24.0876746Z","disk":{"freeGB":836.27,"totalGB":952.35},"processes":[{"group":"dsc","running":false,"name":"DSC exporter"},{"group":"tg","running":false,"name":"TG client"}],"machine":"PINGUIN"}]}