{"machines":[{"timestamp":"2026-07-13T16:06:02.6401119Z","disk":{"freeGB":824.04,"totalGB":3725.12},"processes":[{"group":"dsc","running":false,"name":"DSC exporter"},{"group":"tg","running":true,"name":"TG client"}],"machine":"DESKTOP-HIRREFE"},{"timestamp":"2026-07-13T16:06:14.8050367Z","disk":{"freeGB":383.35,"totalGB":476.07},"processes":[{"group":"dsc","running":false,"name":"DSC exporter"},{"group":"tg","running":false,"name":"TG client"}],"machine":"PRODESK1"},{"timestamp":"2026-07-13T15:54:18.7964625Z","disk":{"freeGB":279.05,"totalGB":476.05},"processes":[{"group":"dsc","running":false,"name":"DSC exporter"},{"group":"tg","running":true,"name":"TG client"}],"machine":"PRODESK2"},{"timestamp":"2026-07-13T15:56:09.8907169Z","disk":{"freeGB":253.09,"totalGB":449.56},"processes":[{"group":"dsc","running":false,"name":"DSC exporter"},{"group":"tg","running":true,"name":"TG client"}],"machine":"QUOKKA"},{"timestamp":"2026-07-13T15:56:42.2752547Z","disk":{"freeGB":214.28,"totalGB":446.48},"processes":[{"group":"dsc","running":false,"name":"DSC exporter"},{"group":"tg","running":true,"name":"TG client"}],"needsRelogin":false,"machine":"DESKTOP-OVAKFQ8"},{"timestamp":"2026-07-13T10:02:19.5884404Z","disk":{"freeGB":1080.15,"totalGB":1853.66},"processes":[{"group":"dsc","running":false,"name":"DSC exporter"},{"group":"tg","running":true,"name":"TG client"}],"machine":"DESKTOP-QKRT7VO"},{"timestamp":"2026-07-13T15:57:01.9364288Z","disk":{"freeGB":30.86,"totalGB":208.45},"processes":[{"group":"dsc","running":false,"name":"DSC exporter"},{"group":"tg","running":true,"name":"TG client"}],"machine":"ASPIRE-V3"},{"timestamp":"2026-07-13T16:02:19.0418203Z","disk":{"freeGB":219.06,"totalGB":952.97},"processes":[{"group":"dsc","running":false,"name":"DSC exporter"},{"group":"tg","running":true,"name":"TG client"}],"machine":"DESKTOP-6EG6J48"},{"timestamp":"2026-07-13T11:06:47.8959975Z","disk":{"freeGB":11.77,"totalGB":232.72},"processes":[{"group":"dsc","running":false,"name":"DSC exporter"},{"group":"tg","running":true,"name":"TG client"}],"needsRelogin":false,"machine":"DESKTOP-N4FRF9P"},{"timestamp":"2026-07-13T15:57:24.4304889Z","disk":{"freeGB":55.71,"totalGB":930.5},"processes":[{"group":"dsc","running":false,"name":"DSC exporter"},{"group":"tg","running":false,"name":"TG client"}],"machine":"ASUS2"},{"timestamp":"2026-04-08T05:15:37.2767272Z","disk":{"freeGB":416.31,"totalGB":476.05},"processes":[{"group":"dsc","running":false,"name":"DSC exporter"},{"group":"tg","running":false,"name":"TG client"}],"needsRelogin":false,"machine":"QIAOTHEBEST"},{"timestamp":"2026-07-10T23:32:36.1376369Z","disk":{"freeGB":843.35,"totalGB":952.35},"processes":[{"group":"dsc","running":false,"name":"DSC exporter"},{"group":"tg","running":false,"name":"TG client"}],"machine":"PINGUIN"}]}