{"machines":[{"timestamp":"2026-05-25T01:21:02.3431037Z","disk":{"freeGB":1183.84,"totalGB":3725.12},"processes":[{"group":"dsc","running":false,"name":"DSC exporter"},{"group":"tg","running":false,"name":"TG client"}],"machine":"DESKTOP-HIRREFE"},{"timestamp":"2026-05-25T01:21:15.1885181Z","disk":{"freeGB":405.45,"totalGB":476.07},"processes":[{"group":"dsc","running":true,"name":"DSC exporter"},{"group":"tg","running":false,"name":"TG client"}],"machine":"PRODESK1"},{"timestamp":"2026-05-25T01:24:18.8562487Z","disk":{"freeGB":122.42,"totalGB":476.05},"processes":[{"group":"dsc","running":true,"name":"DSC exporter"},{"group":"tg","running":true,"name":"TG client"}],"machine":"PRODESK2"},{"timestamp":"2026-05-25T01:26:09.4585497Z","disk":{"freeGB":105.86,"totalGB":449.56},"processes":[{"group":"dsc","running":false,"name":"DSC exporter"},{"group":"tg","running":true,"name":"TG client"}],"machine":"QUOKKA"},{"timestamp":"2026-05-25T01:26:42.7408494Z","disk":{"freeGB":16.18,"totalGB":446.48},"processes":[{"group":"dsc","running":false,"name":"DSC exporter"},{"group":"tg","running":true,"name":"TG client"}],"needsRelogin":false,"machine":"DESKTOP-OVAKFQ8"},{"timestamp":"2026-05-25T01:32:19.3236906Z","disk":{"freeGB":1217.76,"totalGB":1853.66},"processes":[{"group":"dsc","running":false,"name":"DSC exporter"},{"group":"tg","running":true,"name":"TG client"}],"machine":"DESKTOP-QKRT7VO"},{"timestamp":"2026-05-25T01:27:02.4935394Z","disk":{"freeGB":8.38,"totalGB":208.45},"processes":[{"group":"dsc","running":false,"name":"DSC exporter"},{"group":"tg","running":true,"name":"TG client"}],"machine":"ASPIRE-V3"},{"timestamp":"2026-05-25T01:17:17.9679150Z","disk":{"freeGB":31.93,"totalGB":952.97},"processes":[{"group":"dsc","running":false,"name":"DSC exporter"},{"group":"tg","running":true,"name":"TG client"}],"machine":"DESKTOP-6EG6J48"},{"timestamp":"2026-05-25T01:21:46.5503213Z","disk":{"freeGB":15.19,"totalGB":232.72},"processes":[{"group":"dsc","running":false,"name":"DSC exporter"},{"group":"tg","running":true,"name":"TG client"}],"needsRelogin":false,"machine":"DESKTOP-N4FRF9P"},{"timestamp":"2026-05-22T10:32:04.8273728Z","disk":{"freeGB":73.75,"totalGB":930.5},"processes":[{"group":"dsc","running":false,"name":"DSC exporter"},{"group":"tg","running":false,"name":"TG client"}],"machine":"ASUS2"},{"timestamp":"2026-04-08T05:15:37.2767272Z","disk":{"freeGB":416.31,"totalGB":476.05},"processes":[{"group":"dsc","running":false,"name":"DSC exporter"},{"group":"tg","running":false,"name":"TG client"}],"needsRelogin":false,"machine":"QIAOTHEBEST"},{"timestamp":"2026-05-24T21:16:26.1031903Z","disk":{"freeGB":844.97,"totalGB":952.35},"processes":[{"group":"dsc","running":false,"name":"DSC exporter"},{"group":"tg","running":false,"name":"TG client"}],"machine":"PINGUIN"}]}