{"machines":[{"timestamp":"2026-07-22T00:21:02.4472211Z","disk":{"freeGB":854.46,"totalGB":3725.06},"processes":[{"group":"dsc","running":false,"name":"DSC exporter"},{"group":"tg","running":false,"name":"TG client"}],"machine":"DESKTOP-HIRREFE"},{"timestamp":"2026-07-22T00:21:15.1255135Z","disk":{"freeGB":385.61,"totalGB":475.99},"processes":[{"group":"dsc","running":false,"name":"DSC exporter"},{"group":"tg","running":false,"name":"TG client"}],"machine":"PRODESK1"},{"timestamp":"2026-07-22T00:24:18.3793902Z","disk":{"freeGB":264,"totalGB":476.05},"processes":[{"group":"dsc","running":false,"name":"DSC exporter"},{"group":"tg","running":true,"name":"TG client"}],"machine":"PRODESK2"},{"timestamp":"2026-07-22T00:26:09.2713503Z","disk":{"freeGB":225.91,"totalGB":449.56},"processes":[{"group":"dsc","running":false,"name":"DSC exporter"},{"group":"tg","running":true,"name":"TG client"}],"machine":"QUOKKA"},{"timestamp":"2026-07-22T00:26:42.1680631Z","disk":{"freeGB":152.37,"totalGB":446.48},"processes":[{"group":"dsc","running":false,"name":"DSC exporter"},{"group":"tg","running":true,"name":"TG client"}],"needsRelogin":false,"machine":"DESKTOP-OVAKFQ8"},{"timestamp":"2026-07-22T00:17:19.7748849Z","disk":{"freeGB":1078.59,"totalGB":1853.66},"processes":[{"group":"dsc","running":false,"name":"DSC exporter"},{"group":"tg","running":true,"name":"TG client"}],"machine":"DESKTOP-QKRT7VO"},{"timestamp":"2026-07-21T15:57:02.3678661Z","disk":{"freeGB":7.61,"totalGB":208.45},"processes":[{"group":"dsc","running":false,"name":"DSC exporter"},{"group":"tg","running":true,"name":"TG client"}],"machine":"ASPIRE-V3"},{"timestamp":"2026-07-22T00:32:18.2719180Z","disk":{"freeGB":185.78,"totalGB":952.97},"processes":[{"group":"dsc","running":false,"name":"DSC exporter"},{"group":"tg","running":true,"name":"TG client"}],"machine":"DESKTOP-6EG6J48"},{"timestamp":"2026-07-22T00:21:47.0700758Z","disk":{"freeGB":50.62,"totalGB":232.72},"processes":[{"group":"dsc","running":false,"name":"DSC exporter"},{"group":"tg","running":false,"name":"TG client"}],"needsRelogin":false,"machine":"DESKTOP-N4FRF9P"},{"timestamp":"2026-07-21T11:57:24.8721867Z","disk":{"freeGB":61.43,"totalGB":930.43},"processes":[{"group":"dsc","running":false,"name":"DSC exporter"},{"group":"tg","running":false,"name":"TG client"}],"machine":"ASUS2"},{"timestamp":"2026-04-08T05:15:37.2767272Z","disk":{"freeGB":416.31,"totalGB":476.05},"processes":[{"group":"dsc","running":false,"name":"DSC exporter"},{"group":"tg","running":false,"name":"TG client"}],"needsRelogin":false,"machine":"QIAOTHEBEST"},{"timestamp":"2026-07-22T00:31:24.9523127Z","disk":{"freeGB":835.42,"totalGB":952.35},"processes":[{"group":"dsc","running":false,"name":"DSC exporter"},{"group":"tg","running":false,"name":"TG client"}],"machine":"PINGUIN"}]}