{"machines":[{"timestamp":"2026-04-02T20:51:02.7663497Z","disk":{"freeGB":85.88,"totalGB":3725.12},"processes":[{"group":"dsc","running":false,"name":"DSC exporter"},{"group":"tg","running":true,"name":"TG client"}],"machine":"DESKTOP-HIRREFE"},{"timestamp":"2026-04-02T20:51:15.1477715Z","disk":{"freeGB":407.74,"totalGB":476.07},"processes":[{"group":"dsc","running":true,"name":"DSC exporter"},{"group":"tg","running":false,"name":"TG client"}],"machine":"PRODESK1"},{"timestamp":"2026-04-02T20:54:16.7446006Z","disk":{"freeGB":278.14,"totalGB":476.05},"processes":[{"group":"dsc","running":true,"name":"DSC exporter"},{"group":"tg","running":true,"name":"TG client"}],"machine":"PRODESK2"},{"timestamp":"2026-04-02T20:56:09.2802559Z","disk":{"freeGB":219.87,"totalGB":449.56},"processes":[{"group":"dsc","running":false,"name":"DSC exporter"},{"group":"tg","running":true,"name":"TG client"}],"machine":"QUOKKA"},{"timestamp":"2026-04-02T20:56:42.5077551Z","disk":{"freeGB":118.41,"totalGB":446.48},"processes":[{"group":"dsc","running":false,"name":"DSC exporter"},{"group":"tg","running":true,"name":"TG client"}],"needsRelogin":false,"machine":"DESKTOP-OVAKFQ8"},{"timestamp":"2026-04-02T21:02:17.9761579Z","disk":{"freeGB":1336.11,"totalGB":1854.09},"processes":[{"group":"dsc","running":false,"name":"DSC exporter"},{"group":"tg","running":true,"name":"TG client"}],"machine":"DESKTOP-QKRT7VO"},{"timestamp":"2026-03-17T11:57:04.4982360Z","disk":{"freeGB":45.14,"totalGB":208.45},"processes":[{"group":"dsc","running":false,"name":"DSC exporter"},{"group":"tg","running":true,"name":"TG client"}],"machine":"ASPIRE-V3"},{"timestamp":"2026-04-02T21:02:18.2865849Z","disk":{"freeGB":194.82,"totalGB":952.97},"processes":[{"group":"dsc","running":false,"name":"DSC exporter"},{"group":"tg","running":true,"name":"TG client"}],"machine":"DESKTOP-6EG6J48"},{"timestamp":"2026-04-02T20:51:46.9650893Z","disk":{"freeGB":36.4,"totalGB":232.72},"processes":[{"group":"dsc","running":false,"name":"DSC exporter"},{"group":"tg","running":true,"name":"TG client"}],"needsRelogin":false,"machine":"DESKTOP-N4FRF9P"},{"timestamp":"2026-03-30T16:12:24.9648564Z","disk":{"freeGB":74.36,"totalGB":930.5},"processes":[{"group":"dsc","running":false,"name":"DSC exporter"},{"group":"tg","running":false,"name":"TG client"}],"machine":"ASUS2"},{"timestamp":"2026-04-02T21:00:37.3028538Z","disk":{"freeGB":416.38,"totalGB":476.05},"processes":[{"group":"dsc","running":false,"name":"DSC exporter"},{"group":"tg","running":false,"name":"TG client"}],"needsRelogin":false,"machine":"QIAOTHEBEST"},{"timestamp":"2026-04-02T15:55:04.2838131Z","disk":{"freeGB":840.45,"totalGB":952.35},"processes":[{"group":"dsc","running":false,"name":"DSC exporter"},{"group":"tg","running":false,"name":"TG client"}],"machine":"PINGUIN"}]}