{"machines":[{"timestamp":"2026-03-03T18:06:02.9179614Z","disk":{"freeGB":303.98,"totalGB":3725.12},"processes":[{"group":"dsc","running":false,"name":"DSC exporter"},{"group":"tg","running":false,"name":"TG client"}],"machine":"DESKTOP-HIRREFE"},{"timestamp":"2026-03-03T18:06:15.1209028Z","disk":{"freeGB":409.05,"totalGB":476.07},"processes":[{"group":"dsc","running":true,"name":"DSC exporter"},{"group":"tg","running":false,"name":"TG client"}],"machine":"PRODESK1"},{"timestamp":"2026-03-03T18:09:17.9048489Z","disk":{"freeGB":354.19,"totalGB":476.05},"processes":[{"group":"dsc","running":true,"name":"DSC exporter"},{"group":"tg","running":true,"name":"TG client"}],"machine":"PRODESK2"},{"timestamp":"2026-03-03T18:11:09.8286398Z","disk":{"freeGB":268.24,"totalGB":449.56},"processes":[{"group":"dsc","running":false,"name":"DSC exporter"},{"group":"tg","running":true,"name":"TG client"}],"machine":"QUOKKA"},{"timestamp":"2026-03-03T18:11:42.4826601Z","disk":{"freeGB":223.43,"totalGB":446.48},"processes":[{"group":"dsc","running":false,"name":"DSC exporter"},{"group":"tg","running":true,"name":"TG client"}],"needsRelogin":false,"machine":"DESKTOP-OVAKFQ8"},{"timestamp":"2026-03-03T18:02:18.8802427Z","disk":{"freeGB":1399.63,"totalGB":1854.09},"processes":[{"group":"dsc","running":false,"name":"DSC exporter"},{"group":"tg","running":true,"name":"TG client"}],"machine":"DESKTOP-QKRT7VO"},{"timestamp":"2026-03-03T18:12:01.8764783Z","disk":{"freeGB":8.98,"totalGB":208.45},"processes":[{"group":"dsc","running":false,"name":"DSC exporter"},{"group":"tg","running":true,"name":"TG client"}],"machine":"ASPIRE-V3"},{"timestamp":"2026-03-03T18:02:17.5436578Z","disk":{"freeGB":240.89,"totalGB":953.25},"processes":[{"group":"dsc","running":false,"name":"DSC exporter"},{"group":"tg","running":true,"name":"TG client"}],"machine":"DESKTOP-6EG6J48"},{"timestamp":"2026-03-03T18:06:46.6471505Z","disk":{"freeGB":106.64,"totalGB":232.72},"processes":[{"group":"dsc","running":false,"name":"DSC exporter"},{"group":"tg","running":true,"name":"TG client"}],"needsRelogin":false,"machine":"DESKTOP-N4FRF9P"},{"timestamp":"2026-02-25T19:27:25.4414146Z","disk":{"freeGB":63.54,"totalGB":930.57},"processes":[{"group":"dsc","running":false,"name":"DSC exporter"},{"group":"tg","running":false,"name":"TG client"}],"machine":"ASUS2"},{"timestamp":"2026-03-03T18:15:37.1654882Z","disk":{"freeGB":400.23,"totalGB":476.05},"processes":[{"group":"dsc","running":false,"name":"DSC exporter"},{"group":"tg","running":false,"name":"TG client"}],"needsRelogin":false,"machine":"QIAOTHEBEST"},{"timestamp":"2026-03-03T18:01:26.2116830Z","disk":{"freeGB":843.69,"totalGB":952.35},"processes":[{"group":"dsc","running":true,"name":"DSC exporter"},{"group":"tg","running":false,"name":"TG client"}],"machine":"PINGUIN"}]}