{"machines":[{"timestamp":"2026-04-16T16:51:02.5200100Z","disk":{"freeGB":1253.23,"totalGB":3725.12},"processes":[{"group":"dsc","running":false,"name":"DSC exporter"},{"group":"tg","running":true,"name":"TG client"}],"machine":"DESKTOP-HIRREFE"},{"timestamp":"2026-04-16T16:51:15.7365343Z","disk":{"freeGB":400.63,"totalGB":476.07},"processes":[{"group":"dsc","running":true,"name":"DSC exporter"},{"group":"tg","running":false,"name":"TG client"}],"machine":"PRODESK1"},{"timestamp":"2026-04-16T16:54:17.3749727Z","disk":{"freeGB":242.61,"totalGB":476.05},"processes":[{"group":"dsc","running":true,"name":"DSC exporter"},{"group":"tg","running":true,"name":"TG client"}],"machine":"PRODESK2"},{"timestamp":"2026-04-16T16:56:10.1274681Z","disk":{"freeGB":174.54,"totalGB":449.56},"processes":[{"group":"dsc","running":false,"name":"DSC exporter"},{"group":"tg","running":false,"name":"TG client"}],"machine":"QUOKKA"},{"timestamp":"2026-04-16T16:56:42.5949914Z","disk":{"freeGB":55.33,"totalGB":446.48},"processes":[{"group":"dsc","running":false,"name":"DSC exporter"},{"group":"tg","running":true,"name":"TG client"}],"needsRelogin":false,"machine":"DESKTOP-OVAKFQ8"},{"timestamp":"2026-04-16T17:02:18.7551350Z","disk":{"freeGB":1307.62,"totalGB":1854.09},"processes":[{"group":"dsc","running":false,"name":"DSC exporter"},{"group":"tg","running":true,"name":"TG client"}],"machine":"DESKTOP-QKRT7VO"},{"timestamp":"2026-03-17T11:57:04.4982360Z","disk":{"freeGB":45.14,"totalGB":208.45},"processes":[{"group":"dsc","running":false,"name":"DSC exporter"},{"group":"tg","running":true,"name":"TG client"}],"machine":"ASPIRE-V3"},{"timestamp":"2026-04-16T16:47:18.2393657Z","disk":{"freeGB":148.37,"totalGB":952.97},"processes":[{"group":"dsc","running":false,"name":"DSC exporter"},{"group":"tg","running":true,"name":"TG client"}],"machine":"DESKTOP-6EG6J48"},{"timestamp":"2026-04-16T16:51:46.0546847Z","disk":{"freeGB":0,"totalGB":232.72},"processes":[{"group":"dsc","running":false,"name":"DSC exporter"},{"group":"tg","running":false,"name":"TG client"}],"needsRelogin":false,"machine":"DESKTOP-N4FRF9P"},{"timestamp":"2026-04-16T16:57:24.6781621Z","disk":{"freeGB":68.05,"totalGB":930.5},"processes":[{"group":"dsc","running":false,"name":"DSC exporter"},{"group":"tg","running":false,"name":"TG client"}],"machine":"ASUS2"},{"timestamp":"2026-04-08T05:15:37.2767272Z","disk":{"freeGB":416.31,"totalGB":476.05},"processes":[{"group":"dsc","running":false,"name":"DSC exporter"},{"group":"tg","running":false,"name":"TG client"}],"needsRelogin":false,"machine":"QIAOTHEBEST"},{"timestamp":"2026-04-16T17:01:25.7141111Z","disk":{"freeGB":837.29,"totalGB":952.35},"processes":[{"group":"dsc","running":false,"name":"DSC exporter"},{"group":"tg","running":false,"name":"TG client"}],"machine":"PINGUIN"}]}